django_project_setup/__init__.py
django_project_setup/setup_django.py
django_quickstart_setup-0.1.2.dist-info/licenses/LICENSE
django_quickstart_setup-0.1.2.dist-info/METADATA
django_quickstart_setup-0.1.2.dist-info/WHEEL
django_quickstart_setup-0.1.2.dist-info/entry_points.txt
django_quickstart_setup-0.1.2.dist-info/top_level.txt
django_quickstart_setup-0.1.2.dist-info/RECORD
