Metadata-Version: 2.4
Name: django-quickstart-setup
Version: 0.1.2
Summary: A utility to quickly set up Django projects with best practices
Home-page: https://github.com/codingwhiz-BackendDev/django-quickstart-setup
Author: Your Name
Author-email: oluyemiemma2409@gmail.com
Classifier: Programming Language :: Python :: 3
Classifier: License :: OSI Approved :: MIT License
Classifier: Operating System :: OS Independent
Requires-Python: >=3.6
License-File: LICENSE
Requires-Dist: django>=3.0
Dynamic: author
Dynamic: author-email
Dynamic: classifier
Dynamic: description
Dynamic: description-content-type
Dynamic: home-page
Dynamic: license-file
Dynamic: requires-dist
Dynamic: requires-python
Dynamic: summary
